setup.py
crx/__init__.py
crx/writer.py
pycrxlib.egg-info/PKG-INFO
pycrxlib.egg-info/SOURCES.txt
pycrxlib.egg-info/dependency_links.txt
pycrxlib.egg-info/requires.txt
pycrxlib.egg-info/top_level.txt
test/test_writer.py